pytrnsys/__init__.py
pytrnsys/py.typed
pytrnsys/cost_calculation/__init__.py
pytrnsys/cost_calculation/_createCostCalculations.py
pytrnsys/cost_calculation/_economicFunctions.py
pytrnsys/cost_calculation/_resultsWriter.py
pytrnsys/cost_calculation/processType.py
pytrnsys/cost_calculation/_cost_table/__init__.py
pytrnsys/cost_calculation/_cost_table/_annuities.py
pytrnsys/cost_calculation/_cost_table/_componentGroups.py
pytrnsys/cost_calculation/_models/__init__.py
pytrnsys/cost_calculation/_models/common.py
pytrnsys/cost_calculation/_models/input.py
pytrnsys/cost_calculation/_models/output.py
pytrnsys/ddck/__init__.py
pytrnsys/ddck/_parse.py
pytrnsys/ddck/ddck.lark
pytrnsys/ddck/replaceTokens.py
pytrnsys/pdata/__init__.py
pytrnsys/pdata/loadBase.py
pytrnsys/pdata/loadBaseNumpy.py
pytrnsys/pdata/loadInputFile.py
pytrnsys/pdata/processFiles.py
pytrnsys/pdata/processHourly.py
pytrnsys/physprop/__init__.py
pytrnsys/physprop/physProp.py
pytrnsys/plot/__init__.py
pytrnsys/plot/downSizeForPlotting.py
pytrnsys/plot/plotBokeh.py
pytrnsys/plot/plotGle.py
pytrnsys/plot/plotGround.py
pytrnsys/plot/plotMatplotlib.py
pytrnsys/plot/plotTrnsysUtils.py
pytrnsys/plot/comparison/__init__.py
pytrnsys/plot/comparison/_common.py
pytrnsys/plot/comparison/_gle.py
pytrnsys/plot/stylesheets/word.mplstyle
pytrnsys/psim/__init__.py
pytrnsys/psim/checkItProblemsClass.py
pytrnsys/psim/checkSimulationDataClass.py
pytrnsys/psim/conditions.py
pytrnsys/psim/debugProcess.py
pytrnsys/psim/processMonthlyDataBase.py
pytrnsys/psim/processParallel.py
pytrnsys/psim/processParallelTrnsys.py
pytrnsys/psim/processTrnsysBase.py
pytrnsys/psim/processTrnsysDf.py
pytrnsys/psim/processTrnsysFiles.py
pytrnsys/psim/resultsProcessedFile.py
pytrnsys/psim/simulationLoader.py
pytrnsys/report/__init__.py
pytrnsys/report/latexReport.py
pytrnsys/report/latex_doc/EU_Flag_320_213.png
pytrnsys/report/latex_doc/HSRlogo.jpg
pytrnsys/report/latex_doc/LOGOTYPE+EULOGO.png
pytrnsys-0.7.1.dist-info/LICENSE
pytrnsys-0.7.1.dist-info/METADATA
pytrnsys-0.7.1.dist-info/WHEEL
pytrnsys-0.7.1.dist-info/entry_points.txt
pytrnsys-0.7.1.dist-info/top_level.txt
pytrnsys-0.7.1.dist-info/RECORD
