Metadata-Version: 2.1
Name: pytrnsys
Version: 0.7.1
Summary: pytrnsys simulation framework
Home-page: https://pytrnsys.readthedocs.io
Author: Institute for Solar Technology (SPF), OST Rapperswil
Author-email: martin.neugebauer@ost.ch
License: UNKNOWN
Platform: UNKNOWN
Classifier: Programming Language :: Python :: 3
Classifier: License :: OSI Approved :: MIT License
Classifier: Operating System :: Microsoft :: Windows
Requires-Python: >=3.9
License-File: LICENSE
Requires-Dist: numpy
Requires-Dist: scipy
Requires-Dist: pandas
Requires-Dist: matplotlib
Requires-Dist: seaborn
Requires-Dist: bokeh
Requires-Dist: dataclasses-jsonschema
Requires-Dist: lark
